officelyTest/CustomException.py
officelyTest/__init__.py
officelyTest/generator.py
officelyTest/main.py
officelyTest/run.py
officelyTest/stream_handler.py
officelyTest/team_builder/__init__.py
officelyTest/team_builder/graph.py
officelyTest/team_builder/llms/__init__.py
officelyTest/team_builder/llms/azure.py
officelyTest/team_builder/llms/bedrock.py
officelyTest/team_builder/llms/bedrock_tools.py
officelyTest/team_builder/llms/cohere.py
officelyTest/team_builder/llms/enums.py
officelyTest/team_builder/llms/factory.py
officelyTest/team_builder/llms/google.py
officelyTest/team_builder/llms/llm.py
officelyTest/team_builder/llms/openai.py
officelyTest/team_builder/llms/together.py
officelyTest/team_builder/llms/tokenizer.py
officelyTest/team_builder/nodes/__init__.py
officelyTest/team_builder/nodes/enums.py
officelyTest/team_builder/nodes/factory.py
officelyTest/team_builder/nodes/interface.py
officelyTest/team_builder/nodes/jump.py
officelyTest/team_builder/nodes/llm_node.py
officelyTest/team_builder/nodes/node.py
officelyTest/team_builder/nodes/python_node.py
officelyTest/team_builder/nodes/retriver_node.py
officelyTest/team_builder/nodes/text_node.py
officelyTest/team_builder/nodes/filter/__init__.py
officelyTest/team_builder/nodes/filter/enums.py
officelyTest/team_builder/nodes/filter/filter_node.py
officelyTest/team_builder/nodes/filter/interfaces.py
officelyTest-0.1.12.dist-info/LICENSE
officelyTest-0.1.12.dist-info/METADATA
officelyTest-0.1.12.dist-info/WHEEL
officelyTest-0.1.12.dist-info/top_level.txt
officelyTest-0.1.12.dist-info/RECORD
