Metadata-Version: 2.1
Name: officelyTest
Version: 0.1.12
Summary: A brief description of your package
Author: Your Name
Author-email: your.email@example.com
Classifier: Programming Language :: Python :: 3
Classifier: License :: OSI Approved :: MIT License
Classifier: Operating System :: OS Independent
Requires-Python: >=3.8
License-File: LICENSE
Requires-Dist: aiohappyeyeballs==2.3.5
Requires-Dist: aiohttp==3.10.3
Requires-Dist: aiosignal==1.3.1
Requires-Dist: annotated-types==0.7.0
Requires-Dist: anthropic==0.33.1
Requires-Dist: anyio==4.4.0
Requires-Dist: attrs==24.2.0
Requires-Dist: backports.tarfile==1.2.0
Requires-Dist: boto3==1.34.160
Requires-Dist: botocore==1.34.160
Requires-Dist: cachetools==5.4.0
Requires-Dist: certifi==2024.7.4
Requires-Dist: charset-normalizer==3.3.2
Requires-Dist: cohere==5.8.0
Requires-Dist: colorama==0.4.6
Requires-Dist: dataclasses-json==0.6.7
Requires-Dist: defusedxml==0.7.1
Requires-Dist: distro==1.9.0
Requires-Dist: docutils==0.21.2
Requires-Dist: fastavro==1.9.5
Requires-Dist: filelock==3.15.4
Requires-Dist: frozenlist==1.4.1
Requires-Dist: fsspec==2024.6.1
Requires-Dist: google-ai-generativelanguage==0.6.6
Requires-Dist: google-api-core==2.19.1
Requires-Dist: google-api-python-client==2.140.0
Requires-Dist: google-auth==2.33.0
Requires-Dist: google-auth-httplib2==0.2.0
Requires-Dist: google-generativeai==0.7.2
Requires-Dist: googleapis-common-protos==1.63.2
Requires-Dist: grpcio==1.65.4
Requires-Dist: grpcio-status==1.62.3
Requires-Dist: h11==0.14.0
Requires-Dist: httpcore==1.0.5
Requires-Dist: httplib2==0.22.0
Requires-Dist: httpx==0.27.0
Requires-Dist: httpx-sse==0.4.0
Requires-Dist: huggingface-hub==0.24.5
Requires-Dist: idna==3.7
Requires-Dist: importlib-metadata==8.2.0
Requires-Dist: jaraco.classes==3.4.0
Requires-Dist: jaraco.context==5.3.0
Requires-Dist: jaraco.functools==4.0.2
Requires-Dist: jiter==0.5.0
Requires-Dist: jmespath==1.0.1
Requires-Dist: jsonpatch==1.33
Requires-Dist: jsonpointer==3.0.0
Requires-Dist: keyring==25.3.0
Requires-Dist: langchain==0.2.13
Requires-Dist: langchain-anthropic==0.1.22
Requires-Dist: langchain-aws==0.1.16
Requires-Dist: langchain-cohere==0.2.2
Requires-Dist: langchain-community==0.2.12
Requires-Dist: langchain-core==0.2.30
Requires-Dist: langchain-experimental==0.0.64
Requires-Dist: langchain-google-genai==1.0.8
Requires-Dist: langchain-openai==0.1.21
Requires-Dist: langchain-text-splitters==0.2.2
Requires-Dist: langchain-together==0.1.5
Requires-Dist: langsmith==0.1.99
Requires-Dist: markdown-it-py==3.0.0
Requires-Dist: marshmallow==3.21.3
Requires-Dist: mdurl==0.1.2
Requires-Dist: more-itertools==10.4.0
Requires-Dist: multidict==6.0.5
Requires-Dist: mypy-extensions==1.0.0
Requires-Dist: nh3==0.2.18
Requires-Dist: numpy==1.26.4
Requires-Dist: openai==1.40.6
Requires-Dist: orjson==3.10.7
Requires-Dist: packaging==24.1
Requires-Dist: pandas==2.2.2
Requires-Dist: parameterized==0.9.0
Requires-Dist: pinecone-client==5.0.1
Requires-Dist: pinecone-plugin-inference==1.0.3
Requires-Dist: pinecone-plugin-interface==0.0.7
Requires-Dist: pkginfo==1.10.0
Requires-Dist: proto-plus==1.24.0
Requires-Dist: protobuf==4.25.4
Requires-Dist: pyasn1==0.6.0
Requires-Dist: pyasn1-modules==0.4.0
Requires-Dist: pydantic==2.8.2
Requires-Dist: pydantic-core==2.20.1
Requires-Dist: Pygments==2.18.0
Requires-Dist: pyparsing==3.1.2
Requires-Dist: python-dateutil==2.9.0.post0
Requires-Dist: pytz==2024.1
Requires-Dist: PyYAML==6.0.2
Requires-Dist: readme-renderer==44.0
Requires-Dist: regex==2024.7.24
Requires-Dist: requests==2.32.3
Requires-Dist: requests-toolbelt==1.0.0
Requires-Dist: rfc3986==2.0.0
Requires-Dist: rich==13.7.1
Requires-Dist: rsa==4.9
Requires-Dist: s3transfer==0.10.2
Requires-Dist: six==1.16.0
Requires-Dist: sniffio==1.3.1
Requires-Dist: SQLAlchemy==2.0.32
Requires-Dist: tabulate==0.9.0
Requires-Dist: tenacity==8.5.0
Requires-Dist: tiktoken==0.7.0
Requires-Dist: tokenizers==0.20.0
Requires-Dist: tqdm==4.66.5
Requires-Dist: twine==5.1.1
Requires-Dist: types-requests==2.32.0.20240712
Requires-Dist: typing-inspect==0.9.0
Requires-Dist: typing-extensions==4.12.2
Requires-Dist: tzdata==2024.1
Requires-Dist: uritemplate==4.1.1
Requires-Dist: urllib3==2.2.2
Requires-Dist: yarl==1.9.4
Requires-Dist: zipp==3.20.0
